{"stair1":{"name":"stair1","dots":[{"mainHandle":{"x":58.862876254180605,"y":123.96878483835009},"nextHandle":{"x":59.75473801560758,"y":161.42697881828317},"prevHandle":null},{"mainHandle":{"x":65.99777034559644,"y":231.88405797101453},"nextHandle":null,"prevHandle":{"x":60.64659977703457,"y":197.10144927536237}}],"breakpath":false,"objects":{"hero":{"animation":"stairCaseWalk","speed":2}}},"stairToTree":{"name":"stairToTree","dots":[{"mainHandle":{"x":65.99777034559644,"y":231.88405797101453},"nextHandle":{"x":76.00771961188192,"y":228.55311023664052},"prevHandle":null},{"mainHandle":{"x":322.67303102625294,"y":296.8973747016706},"nextHandle":{"x":352.9077935411864,"y":308.1201119361541},"prevHandle":{"x":290.38792975004,"y":285.5434944560179}},{"mainHandle":{"x":401.90930787589497,"y":282.57756563245823},"nextHandle":null,"prevHandle":{"x":378.99761336515513,"y":297.85202863961814}}],"breakpath":false,"objects":{"hero":{"animation":"new","speed":3}}},"treeToBucket":{"name":"treeToBucket","dots":[{"mainHandle":{"x":598.5680190930788,"y":362.76849642004765},"nextHandle":{"x":570.0204500706957,"y":383.3698030634573},"prevHandle":null},{"mainHandle":{"x":499.28400954653927,"y":336.9928400954654},"nextHandle":null,"prevHandle":{"x":542.2434367541766,"y":345.58472553699283}}],"breakpath":true,"objects":{"hero":{"animation":"new","speed":3}}},"bucketToGround":{"name":"bucketToGround","dots":[{"mainHandle":{"x":598.5680190930788,"y":362.76849642004765},"nextHandle":{"x":551.6397060882011,"y":287.96498905908095},"prevHandle":null},{"mainHandle":{"x":570.8830548926014,"y":789.4988066825777},"nextHandle":null,"prevHandle":{"x":575.2720912085513,"y":666.0831509846827}}],"breakpath":false,"objects":{"hero":{"animation":"stairCaseWalk","speed":2},"villain":{"animation":"animation","speed":4}}},"groundTreeToLeft":{"name":"groundTreeToLeft","dots":[{"mainHandle":{"x":570.8830548926014,"y":789.4988066825777},"nextHandle":{"x":443.9140811455847,"y":785.6801909307875},"prevHandle":null},{"mainHandle":{"x":145.45454545454547,"y":774.921630094044},"nextHandle":null,"prevHandle":{"x":359.87460815047024,"y":764.8902821316615}}],"breakpath":false,"objects":{"hero":{"animation":"new","speed":3},"villain2":{"animation":"animation","speed":4}}},"stair2":{"name":"stair2","dots":[{"mainHandle":{"x":82.94314381270902,"y":378.1493868450391},"nextHandle":{"x":76.70011148272017,"y":332.6644370122631},"prevHandle":null},{"mainHandle":{"x":65.99777034559644,"y":231.88405797101453},"nextHandle":null,"prevHandle":{"x":73.46897507735942,"y":292.5987712954611}}],"breakpath":false,"objects":{"hero":{"animation":"stairCaseWalk","speed":2}}},"treeInside":{"name":"treeInside","dots":[{"mainHandle":{"x":401.90930787589497,"y":282.57756563245823},"nextHandle":{"x":434.3675417661097,"y":291.16945107398567},"prevHandle":null},{"mainHandle":{"x":499.28400954653927,"y":336.9928400954654},"nextHandle":null,"prevHandle":{"x":438.94988066825766,"y":339.3794749403341}}],"breakpath":false,"objects":{"hero":{"animation":"new","speed":3}}},"birdTreePath":{"name":"birdTreePath","dots":[{"mainHandle":{"x":579.4749403341289,"y":357.99522673031026},"nextHandle":{"x":772.3150357995227,"y":302.6252983293556},"prevHandle":null},{"mainHandle":{"x":798.7460815047023,"y":624.4514106583073},"nextHandle":null,"prevHandle":{"x":701.5389679861739,"y":606.0226992166748}}],"breakpath":false,"objects":{"villain2":{"animation":"animation","speed":4}}},"treeToSemaphore":{"name":"treeToSemaphore","dots":[{"mainHandle":{"x":570.8830548926014,"y":789.4988066825777},"nextHandle":{"x":762.3824451410659,"y":788.7147335423198},"prevHandle":null},{"mainHandle":{"x":873.9811912225706,"y":762.3824451410659},"nextHandle":{"x":1087.1473354231975,"y":784.9529780564264},"prevHandle":{"x":830.0940438871474,"y":759.8746081504703}},{"mainHandle":{"x":1411.9122257053293,"y":769.9059561128528},"nextHandle":null,"prevHandle":{"x":1108.4639498432603,"y":756.1128526645768}}],"breakpath":false,"objects":{"hero":{"animation":"new","speed":3}}},"semaphoreBreakPath":{"name":"semaphoreBreakPath","dots":[{"mainHandle":{"x":1411.9122257053293,"y":769.9059561128528},"nextHandle":{"x":1479.6238244514109,"y":769.9059561128528},"prevHandle":null},{"mainHandle":{"x":1673.9811912225707,"y":783.6990595611286},"nextHandle":null,"prevHandle":{"x":1612.5391849529783,"y":781.191222570533}}],"breakpath":true,"objects":{"hero":{"animation":"new","speed":3}}},"semaphoreToTV":{"name":"semaphoreToTV","dots":[{"mainHandle":{"x":1673.9811912225707,"y":783.6990595611286},"nextHandle":{"x":2003.7617554858937,"y":788.7147335423198},"prevHandle":null},{"mainHandle":{"x":2050.1567398119123,"y":738.5579937304076},"nextHandle":null,"prevHandle":{"x":1809.4043887147336,"y":776.1755485893417}}],"breakpath":false,"objects":{"hero":{"animation":"new","speed":3}}},"semaphoreVillainPath":{"name":"semaphoreVillainPath","dots":[{"mainHandle":{"x":1661.4420062695926,"y":614.4200626959248},"nextHandle":{"x":1694.7962382445141,"y":616.1755485893418},"prevHandle":null},{"mainHandle":{"x":1722.884012539185,"y":619.435736677116},"nextHandle":null,"prevHandle":{"x":1673.9811912225707,"y":621.9435736677117}}],"breakpath":false},"birdTreePath2":{"name":"birdTreePath2","dots":[{"mainHandle":{"x":798.7460815047023,"y":624.4514106583073},"nextHandle":{"x":866.4576802507838,"y":631.9749216300941},"prevHandle":null},{"mainHandle":{"x":1065.8307210031348,"y":427.58620689655174},"nextHandle":null,"prevHandle":{"x":989.3416927899688,"y":377.42946708463955}}],"breakpath":false}}